webkitflaskpy/__init__.py
webkitflaskpy/authed_blueprint.py
webkitflaskpy/database.py
webkitflaskpy/ipc_manager.py
webkitflaskpy/mock_app.py
webkitflaskpy/response.py
webkitflaskpy/util.py
webkitflaskpy-0.7.1.dist-info/LICENSE
webkitflaskpy-0.7.1.dist-info/METADATA
webkitflaskpy-0.7.1.dist-info/WHEEL
webkitflaskpy-0.7.1.dist-info/top_level.txt
webkitflaskpy-0.7.1.dist-info/RECORD
