Metadata-Version: 2.1
Name: webkitflaskpy
Version: 0.7.1
Summary: Library supporting the WebKit Team's flask based web services.
Home-page: https://github.com/WebKit/WebKit/tree/main/Tools/Scripts/libraries/webkitflaskpy
Author: Jonathan Bedard
Author-email: jbedard@apple.com
License: Modified BSD
Keywords: web javascript webkit
Classifier: Development Status :: 4 - Beta
Classifier: Framework :: Flask
Classifier: Intended Audience :: Developers
Classifier: License :: OSI Approved :: BSD License
Classifier: Operating System :: MacOS
Classifier: Natural Language :: English
Classifier: Programming Language :: Python :: 3 :: Only
Classifier: Topic :: Software Development :: Libraries :: Python Modules
Classifier: Topic :: Software Development :: Testing
License-File: LICENSE
Requires-Dist: fakeredis
Requires-Dist: Flask
Requires-Dist: Flask-Cors
Requires-Dist: gunicorn
Requires-Dist: redis
Requires-Dist: webkitcorepy
